smplstack.py
smplstack-0.1.0.dist-info/WHEEL
smplstack-0.1.0.dist-info/METADATA
smplstack-0.1.0.dist-info/RECORD
